encord_active_components/__init__.py
encord_active_components/frontend/dist/packaged/assets/annotations-278aa65e.svg
encord_active_components/frontend/dist/packaged/assets/classes-d8759926.svg
encord_active_components/frontend/dist/packaged/assets/default_project_image-d39f461e.webp
encord_active_components/frontend/dist/packaged/assets/empty-aab39c98.svg
encord_active_components/frontend/dist/packaged/assets/encord-import-1cb3a664.svg
encord_active_components/frontend/dist/packaged/assets/file-image-f807a638.svg
encord_active_components/frontend/dist/packaged/assets/import-b86d8e5d.svg
encord_active_components/frontend/dist/packaged/assets/index-48ccc207.css
encord_active_components/frontend/dist/packaged/assets/index-a4c904d4.js
encord_active_components/frontend/dist/packaged/favicon.ico
encord_active_components/frontend/dist/packaged/index.html
encord_active_components/frontend/dist/production/assets/annotations-278aa65e.svg
encord_active_components/frontend/dist/production/assets/classes-d8759926.svg
encord_active_components/frontend/dist/production/assets/default_project_image-d39f461e.webp
encord_active_components/frontend/dist/production/assets/empty-aab39c98.svg
encord_active_components/frontend/dist/production/assets/encord-import-1cb3a664.svg
encord_active_components/frontend/dist/production/assets/file-image-f807a638.svg
encord_active_components/frontend/dist/production/assets/import-b86d8e5d.svg
encord_active_components/frontend/dist/production/assets/index-48ccc207.css
encord_active_components/frontend/dist/production/assets/index-daafec8b.js
encord_active_components/frontend/dist/production/favicon.ico
encord_active_components/frontend/dist/production/index.html
encord_active_components/frontend/dist/sandbox/assets/annotations-278aa65e.svg
encord_active_components/frontend/dist/sandbox/assets/classes-d8759926.svg
encord_active_components/frontend/dist/sandbox/assets/default_project_image-d39f461e.webp
encord_active_components-0.0.33.dist-info/METADATA
encord_active_components-0.0.33.dist-info/WHEEL
encord_active_components-0.0.33.dist-info/RECORD
